[
    {
        "id": 1,
        "type": "point",
        "name": "Info-Stand",
        "kategori": "Info",
        "location": [50.833, 12.9206]
    },
    {
        "id": 2,
        "type": "point",
        "name": "Erste-Hilfe-Station",
        "kategori": "Info",
        "location": [50.834045, 12.919614]
    },
    {
        "id": 11,
        "type": "point",
        "name": "WC Jakobikirchplatz",
        "kategori": "Sanitär",
        "location": [50.833226, 12.919391]
    },
    {
        "id": 12,
        "type": "point",
        "name": "WC Bretgasse",
        "kategori": "Sanitär",
        "location": [50.832157, 12.919278],
        "description": "Barrierefreie Toilettenanlage"
    }
]